showcode_forge/__init__.py
showcode_forge/__main__.py
showcode_forge/compilers/__init__.py
showcode_forge/compilers/compilers.py
showcode_forge/compilers/pytest_compiler.py
showcode_forge/compilers/pytest_decorator.py
showcode_forge/compilers/question_parser.py
showcode_forge/extractors/__init__.py
showcode_forge/extractors/extractor.py
showcode_forge/extractors/html_writer.py
showcode_forge/extractors/python_extractors/__init__.py
showcode_forge/extractors/python_extractors/pytest_extractor.py
showcode_forge/extractors/python_extractors/pytest_scforge_extractor.py
showcode_forge/extractors/python_extractors/python_extractor.py
showcode_forge/extractors/python_extractors/unittest_extractor.py
showcode_forge/scaffolding/__init__.py
showcode_forge/scaffolding/pytest_scaffolding.py
showcode_forge/scaffolding/scaffolding.py
showcode_forge/scaffolding/shared_scaffolding.py
showcode_forge/shared/__init__.py
showcode_forge/shared/types.py
showcode_forge/validator/__init__.py
showcode_forge/validator/validator.py
showcode_forge-0.11.dist-info/LICENSE
showcode_forge-0.11.dist-info/METADATA
showcode_forge-0.11.dist-info/WHEEL
showcode_forge-0.11.dist-info/entry_points.txt
showcode_forge-0.11.dist-info/top_level.txt
showcode_forge-0.11.dist-info/RECORD
