Metadata-Version: 2.1
Name: showcode-forge
Version: 0.11
Summary: Tools for generating code from custom ShowCode Forge questions
Home-page: https://github.com/tituszban/showcode_forge
Author: Titusz Ban
Author-email: tituszban@gmail.com
License: mit
Keywords: showcode
Platform: UNKNOWN
Classifier: Development Status :: 4 - Beta
Classifier: Topic :: Software Development :: Build Tools
Classifier: License :: OSI Approved :: MIT License
Classifier: Programming Language :: Python :: 3
Classifier: Programming Language :: Python :: 3.7
License-File: LICENSE
Requires-Dist: pytest
Requires-Dist: markdown
